setup.py
us_census/__init__.py
us_census/household.py
us_census/population.py
us_census/us_census.py
us_census.egg-info/PKG-INFO
us_census.egg-info/SOURCES.txt
us_census.egg-info/dependency_links.txt
us_census.egg-info/requires.txt
us_census.egg-info/top_level.txt
us_census/api_variable_lookup/__init__.py
us_census/api_variable_lookup/parse_api_variable_household.py
us_census/api_variable_lookup/parse_api_variable_population.py