Metadata-Version: 1.1
Name: us-census
Version: 0.1.4
Summary: Python wrapper for intuitively querying US Census SF1 and SF2 2010
Home-page: https://github.com/linanqiu/us_census
Author: Linan Qiu
Author-email: linanqiu@gmail.com
License: MIT
Keywords: census sf1 sf2 population household usa us
Platform: UNKNOWN
Classifier: Development Status :: 3 - Alpha
Classifier: Intended Audience :: Developers
Classifier: Intended Audience :: Education
Classifier: Intended Audience :: Financial and Insurance Industry
Classifier: Intended Audience :: Healthcare Industry
Classifier: Intended Audience :: Information Technology
Classifier: Intended Audience :: Science/Research
Classifier: Topic :: Scientific/Engineering :: Information Analysis
Classifier: License :: OSI Approved :: MIT License
Classifier: Programming Language :: Python :: 3.3
Classifier: Programming Language :: Python :: 3.4
Classifier: Programming Language :: Python :: 3.5
